{
    "initiatives": [
      {
        "title": "Plastic-Free Living",
        "description": "Reduce your use of single-use plastics to minimize environmental impact.",
        "steps": [
          "Bring a reusable water bottle.",
          "Use cloth bags for groceries.",
          "Avoid plastic straws and cutlery.",
          "Choose products with minimal packaging."
        ],
        "resources": {
          "articles": [
            {
              "title": "The Impact of Plastic on Oceans",
              "url": "https://example.com/plastic-oceans"
            }
          ],
          "videos": [
            {
              "title": "Living Plastic-Free: A Documentary",
              "url": "https://example.com/plastic-free-doc"
            }
          ]
        }
      },
      {
        "title": "Energy-Efficient Homes",
        "description": "Implement practices to make your home more energy-efficient.",
        "steps": [
          "Switch to LED light bulbs.",
          "Install a programmable thermostat.",
          "Unplug electronics when not in use.",
          "Seal gaps and insulate your home."
        ],
        "resources": {
          "articles": [
            {
              "title": "Tips for an Energy-Efficient Home",
              "url": "https://example.com/energy-efficient-tips"
            }
          ],
          "videos": [
            {
              "title": "Energy-Efficient Home Makeover",
              "url": "https://example.com/home-makeover"
            }
          ]
        }
      },
      {
        "title": "Community Garden Project",
        "description": "Contribute to a local community garden for sustainable living.",
        "steps": [
          "Volunteer time for garden maintenance.",
          "Donate seeds or plants.",
          "Attend community gardening workshops.",
          "Promote garden produce sharing within the community."
        ],
        "resources": {
          "articles": [
            {
              "title": "Benefits of Community Gardens",
              "url": "https://example.com/community-garden-benefits"
            }
          ],
          "videos": [
            {
              "title": "Growing Together: Community Gardens Impact",
              "url": "https://example.com/growing-together"
            }
          ]
        }
      },
      {
        "title": "Waste-Free Lunch Challenge",
        "description": "Pack your lunch with minimal waste to reduce environmental impact.",
        "steps": [
          "Use reusable containers and utensils.",
          "Choose snacks with eco-friendly packaging.",
          "Avoid single-use plastic wrap.",
          "Compost organic waste."
        ],
        "resources": {
          "articles": [
            {
              "title": "Guide to a Waste-Free Lunch",
              "url": "https://example.com/waste-free-lunch-guide"
            }
          ],
          "videos": [
            {
              "title": "Zero-Waste Lunchbox Ideas",
              "url": "https://example.com/zero-waste-lunchbox"
            }
          ]
        }
      },
      {
        "title": "Bike to Work Initiative",
        "description": "Reduce carbon emissions by biking to work instead of driving.",
        "steps": [
          "Plan a bike-friendly route to work.",
          "Invest in a reliable bike and safety gear.",
          "Join local bike-to-work events.",
          "Encourage coworkers to join the initiative."
        ],
        "resources": {
          "articles": [
            {
              "title": "Benefits of Biking to Work",
              "url": "https://example.com/bike-to-work-benefits"
            }
          ],
          "videos": [
            {
              "title": "Commuting by Bike: A Healthy Choice",
              "url": "https://example.com/bike-commuting"
            }
          ]
        }
      },
      {
        "title": "Eco-Friendly Home Cleaning",
        "description": "Switch to sustainable cleaning practices for a healthier home and planet.",
        "steps": [
          "Make homemade cleaning solutions.",
          "Use reusable cleaning cloths.",
          "Choose eco-friendly cleaning products.",
          "Properly dispose of hazardous cleaning waste."
        ],
        "resources": {
          "articles": [
            {
              "title": "Green Cleaning Tips for a Healthy Home",
              "url": "https://example.com/green-cleaning-tips"
            }
          ],
          "videos": [
            {
              "title": "DIY Eco-Friendly Cleaning Hacks",
              "url": "https://example.com/eco-friendly-cleaning-hacks"
            }
          ]
        }
      }
    ]
  }


